request_handler/__init__.py
request_handler/handling.py
request_handler-0.1.3.dist-info/METADATA
request_handler-0.1.3.dist-info/WHEEL
request_handler-0.1.3.dist-info/top_level.txt
request_handler-0.1.3.dist-info/RECORD
