Metadata-Version: 2.1
Name: request-handler
Version: 0.1.3
Summary: Request handler library
Author: Kevin van Liebergen
Author-email: example@email.com
License: MIT
Project-URL: Home page, https://github.com/KevinLiebergen/request_handler
Platform: UNKNOWN
Classifier: Intended Audience :: Developers
Classifier: License :: OSI Approved :: MIT License
Classifier: Programming Language :: Python
Classifier: Programming Language :: Python :: 3
Classifier: Programming Language :: Python :: 3.6
Classifier: Programming Language :: Python :: 3.7
Classifier: Programming Language :: Python :: 3.8
Classifier: Programming Language :: Python :: 3.9
Classifier: Operating System :: OS Independent
Requires-Dist: requests
